HISTORY.rst
LICENSE
MANIFEST.in
README.rst
setup.py
wac.py
wac.egg-info/PKG-INFO
wac.egg-info/SOURCES.txt
wac.egg-info/dependency_links.txt
wac.egg-info/requires.txt
wac.egg-info/top_level.txt